primenumbersrangepackage/__init__.py
primenumbersrangepackage/primenumbersrangepackage.py
primenumbersrangeckage-0.0.1.dist-info/METADATA
primenumbersrangeckage-0.0.1.dist-info/WHEEL
primenumbersrangeckage-0.0.1.dist-info/top_level.txt
primenumbersrangeckage-0.0.1.dist-info/RECORD
