Metadata-Version: 2.1
Name: primenumbersrangeckage
Version: 0.0.1
Summary: This code shows a range of prime numbers based on the minimum and maximum numbers the user prompts
Home-page: https://github.com/lucasvenicius19/primenumbersrangepackage.git
Author: Lucas Venicius Alves Santos
Author-email: lucas.alves.santos19@gmail.com
Requires-Python: >=3.10
